{
  "version": "2026-05-17-discord-nasa-workbench-report-v1",
  "updated": "2026-05-17",
  "headline": "NASA Workbench recipe report added",
  "message": "A Discord report was logged for missing NASA Workbench rocket crafting recipes.",
  "items": [
    {
      "id": "data-nasa-workbench-001",
      "type": "bug",
      "area": "Data / recipe",
      "title": "Missing NASA Workbench rocket crafting recipes",
      "status": "investigating",
      "summary": "Discord report: some rocket crafting recipes are missing, especially recipes made in the NASA Workbench.",
      "resolution": "Needs parser/data support for NASA Workbench recipe type or a confirmed recipe data source.",
      "public": true
    },
    {
      "id": "feedback-board-001",
      "type": "feature",
      "area": "Feedback",
      "title": "Public reports and votes tab",
      "status": "done",
      "summary": "Added a public Reports / votes tab that reads GitHub Issues.",
      "resolution": "Users can search bugs/suggestions, filter open/closed reports, and use GitHub thumbs-up reactions as priority votes.",
      "public": true
    },
    {
      "id": "official-status-001",
      "type": "policy",
      "area": "Feedback",
      "title": "Official maintainer status clarified",
      "status": "done",
      "summary": "Feedback reports are public discussion, but final answers are only official when published by the maintainer.",
      "resolution": "The Status / updates panel is the official notification channel for fixed, done, changed, or declined reports.",
      "public": true
    },
    {
      "id": "feedback-001",
      "type": "feature",
      "area": "Feedback",
      "title": "Feedback panel added",
      "status": "done",
      "summary": "Added a Feedback button for bug reports, suggestions, and update status.",
      "resolution": "Users can copy a formatted report or open a prefilled GitHub issue.",
      "public": true
    },
    {
      "id": "flow-zoom-001",
      "type": "bug",
      "area": "gtnh-flow",
      "title": "Diagram viewer was annoying to view",
      "status": "changed",
      "summary": "Added zoom/pan controls for the gtnh-flow viewer.",
      "resolution": "Implemented with viewer-local zoom controls instead of resizing the whole page.",
      "public": true
    },
    {
      "id": "planner-filter-001",
      "type": "suggestion",
      "area": "Planner",
      "title": "Planner filters were too vague",
      "status": "changed",
      "summary": "Planner filter wording was expanded with explanations.",
      "resolution": "Changed checkbox labels and grouped free inputs separately from recursive expansion options.",
      "public": true
    }
  ]
}
